{"id":1,"nombre":"JAVIER","apellido":"SEIJIDO","edad":"42","genero":"masculino","fnacimiento":"01-01-36","dni":"555","telefonomovil":"5555","email":"JSEIJIDO@URBASER.COM.AR","dir_calle":"PRUDAN","num_calle":"150","localidad":"S","escalafon":"O","falta":"01-01-1990","fbaja":"16-10-2017","info":"aaaaaaaaaaaa"}
{"id":2,"nombre":"DIEGO","apellido":"MOREIRA","edad":"29","genero":"masculino","fnacimiento":"01-01-98","dni":"22","telefonomovil":"111","email":"DMOREIRA@TOSA-URBASER.COM.AR","dir_calle":"PRUDAN","num_calle":"150","localidad":"S","escalafon":"O","falta":"01-01-1990","fbaja":"16-10-2017","info":"kkkkkkkkkkkk"}
{"id":3,"nombre":"MARCELO","apellido":"GY","edad":"44","genero":"masculino","fnacimiento":"01-01-1978","dni":"444444","telefonomovil":"1158699987","email":"JSEIJIDO2k2@URBASER.COM.AR","dir_calle":"PRUDAN","num_calle":"150","localidad":"V","escalafon":"SO","falta":"01-01-1990","fbaja":"16-10-2017","info":"WWWWWWWWWWWW"}
{"id":4,"nombre":"PEPE","apellido":"PEREZ","edad":"22","genero":"masculino","fnacimiento":"01-01-1945","dni":"22","telefonomovil":"222","email":"JSEIJIDO2k2RRR@URBASER.COM.AR","dir_calle":"PRUDAN","num_calle":"150","localidad":"S","escalafon":"O","falta":"01-01-1990","fbaja":"16-10-2017","info":"QQQQQQQQQ"}
{"id":5,"nombre":"GG","apellido":"GGG","edad":"20","genero":"masculino","fnacimiento":"01-01-88","dni":"333","telefonomovil":"333333","email":"JSEIJIDO22@URBASER.COM.ARfr","dir_calle":"PRUDAN","num_calle":"150","localidad":"S","escalafon":"O","falta":"01-01-1990","fbaja":"16-10-2017","info":"wwwwwwwwwwwwwwwwwwwww"}
{"id":6,"nombre":"PEDRO","apellido":"PEREZ","edad":"36","genero":"masculino","fnacimiento":"01-01-2000","dni":"25888888","telefonomovil":"445556632","email":"PEDRO@PEDRO.COM","dir_calle":"PU","num_calle":"999","localidad":"V","escalafon":"SJ","falta":"01-01-1990","fbaja":"19-10-2017","info":"OKOKOKOKOKKOKOKOKO"}
